pydantic_sqlalchemy_deco/__init__.py
pydantic_sqlalchemy_deco/decorator.py
pydantic_sqlalchemy_deco/py.typed
pydantic_sqlalchemy_deco-0.0.4.dist-info/METADATA
pydantic_sqlalchemy_deco-0.0.4.dist-info/WHEEL
pydantic_sqlalchemy_deco-0.0.4.dist-info/licenses/LICENSE
pydantic_sqlalchemy_deco-0.0.4.dist-info/RECORD
